json_spec-0.10.1.dist-info/DESCRIPTION.rst
json_spec-0.10.1.dist-info/METADATA
json_spec-0.10.1.dist-info/RECORD
json_spec-0.10.1.dist-info/WHEEL
json_spec-0.10.1.dist-info/entry_points.txt
json_spec-0.10.1.dist-info/metadata.json
json_spec-0.10.1.dist-info/top_level.txt
jsonspec/__init__.py
jsonspec/__main__.py
jsonspec/_version.py
jsonspec/cli.py
jsonspec/driver.py
jsonspec/misc/__init__.py
jsonspec/misc/schemas/draft-03/card.json
jsonspec/misc/schemas/draft-03/hyper-schema.json
jsonspec/misc/schemas/draft-03/json-ref.json
jsonspec/misc/schemas/draft-03/links.json
jsonspec/misc/schemas/draft-03/schema.json
jsonspec/misc/schemas/draft-04/hyper-schema.json
jsonspec/misc/schemas/draft-04/schema.json
jsonspec/operations/__init__.py
jsonspec/operations/bases.py
jsonspec/operations/exceptions.py
jsonspec/pointer/__init__.py
jsonspec/pointer/bases.py
jsonspec/pointer/exceptions.py
jsonspec/pointer/stages.py
jsonspec/reference/__init__.py
jsonspec/reference/bases.py
jsonspec/reference/exceptions.py
jsonspec/reference/providers.py
jsonspec/reference/util.py
jsonspec/validators/__init__.py
jsonspec/validators/bases.py
jsonspec/validators/draft03.py
jsonspec/validators/draft04.py
jsonspec/validators/exceptions.py
jsonspec/validators/factorize.py
jsonspec/validators/formats.py
jsonspec/validators/pointer_util.py
jsonspec/validators/util.py
