Metadata-Version: 1.1
Name: json-spec
Version: 0.10.1
Summary: Implements JSON Schema, JSON Pointer and JSON Reference.
Home-page: http://py.errorist.io/json-spec
Author: Xavier Barbosa
Author-email: clint.northwood@gmail.com
License: BSD
Keywords: json,utilitaries,validation,json-pointer,json-reference,json-schema
Platform: UNKNOWN
Classifier: Development Status :: 4 - Beta
Classifier: Environment :: Console
Classifier: Environment :: OpenStack
Classifier: Intended Audience :: Developers
Classifier: Intended Audience :: Information Technology
Classifier: License :: OSI Approved :: Apache Software License
Classifier: Operating System :: OS Independent
Classifier: Programming Language :: Python
Classifier: Programming Language :: Python :: 2
Classifier: Programming Language :: Python :: 2.7
Classifier: Programming Language :: Python :: 3
Classifier: Programming Language :: Python :: 3.3
Classifier: Programming Language :: Python :: 3.4
Classifier: Programming Language :: Python :: 3.5
